LICENSE.txt
MANIFEST.in
README.md
README_BACKUP_5571.md
README_BASE_5571.md
README_LOCAL_5571.md
README_REMOTE_5571.md
setup.py
django_imperavi_widget.egg-info/PKG-INFO
django_imperavi_widget.egg-info/SOURCES.txt
django_imperavi_widget.egg-info/dependency_links.txt
django_imperavi_widget.egg-info/requires.txt
django_imperavi_widget.egg-info/top_level.txt
imperavi/__init__.py
imperavi/admin.py
imperavi/forms.py
imperavi/urls.py
imperavi/views.py
imperavi/widget.py
imperavi/static/imperavi/jquery.js
imperavi/static/imperavi/redactor/redactor.js
imperavi/static/imperavi/redactor/css/docstyle.css
imperavi/static/imperavi/redactor/css/redactor-font.eot
imperavi/static/imperavi/redactor/css/redactor-iframe.css
imperavi/static/imperavi/redactor/css/redactor.css
imperavi/static/imperavi/redactor/langs/bg.js
imperavi/static/imperavi/redactor/langs/by.js
imperavi/static/imperavi/redactor/langs/cs.js
imperavi/static/imperavi/redactor/langs/de.js
imperavi/static/imperavi/redactor/langs/en.js
imperavi/static/imperavi/redactor/langs/es.js
imperavi/static/imperavi/redactor/langs/fi.js
imperavi/static/imperavi/redactor/langs/fr.js
imperavi/static/imperavi/redactor/langs/hr.js
imperavi/static/imperavi/redactor/langs/hu.js
imperavi/static/imperavi/redactor/langs/it.js
imperavi/static/imperavi/redactor/langs/ja.js
imperavi/static/imperavi/redactor/langs/ko.js
imperavi/static/imperavi/redactor/langs/lv.js
imperavi/static/imperavi/redactor/langs/nl.js
imperavi/static/imperavi/redactor/langs/pl.js
imperavi/static/imperavi/redactor/langs/pt_br.js
imperavi/static/imperavi/redactor/langs/ru.js
imperavi/static/imperavi/redactor/langs/sk.js
imperavi/static/imperavi/redactor/langs/sq.js
imperavi/static/imperavi/redactor/langs/tr.js
imperavi/static/imperavi/redactor/langs/ua.js
imperavi/static/imperavi/redactor/langs/zh_cn.js
imperavi/static/imperavi/redactor/plugins/clips/clips.css
imperavi/static/imperavi/redactor/plugins/clips/clips.js
imperavi/static/imperavi/redactor/plugins/clips/index.html
imperavi/static/imperavi/redactor/plugins/cut/cut.js
imperavi/static/imperavi/redactor/plugins/fontcolor/fontcolor.js
imperavi/static/imperavi/redactor/plugins/fontcolor/index.html
