Metadata-Version: 1.0
Name: django-imperavi-widget
Version: 0.0.3
Summary: A django admin widget to render a         text field as beautiful Imperavi WYSIWYG editor http://redactorjs.com/
Home-page: https://github.com/dzaytsev91/django-imperavi-widget
Author: Zaytsev Dmitriy
Author-email: zaytsev_dmitriy@aol.com
License: MIT License
Keywords: django admin imperavi widget
Platform: any
